LICENSE
README.md
setup.py
vpnr_client/__init__.py
vpnr_client/__main__.py
vpnr_client/config.py
vpnr_client/info.py
vpnr_client/logger.py
vpnr_client/parser.py
vpnr_client/tunnel.py
vpnr_client/utils.py
vpnroulette.egg-info/PKG-INFO
vpnroulette.egg-info/SOURCES.txt
vpnroulette.egg-info/dependency_links.txt
vpnroulette.egg-info/entry_points.txt
vpnroulette.egg-info/requires.txt
vpnroulette.egg-info/top_level.txt