Metadata-Version: 2.1
Name: vpnroulette
Version: 0.0.1
Summary: VPNROULETTE CLIENT
Home-page: https://github.com/vpnroulette/vpnr-client
Author: Vpnroulette
Author-email: hello@vpnroulette.com
License: Apache
Platform: UNKNOWN
Classifier: Development Status :: 4 - Beta
Classifier: Intended Audience :: End Users/Desktop
Classifier: License :: OSI Approved :: Apache Software License
Classifier: Operating System :: POSIX :: Linux
Classifier: Operating System :: MacOS
Classifier: Programming Language :: Python
Classifier: Programming Language :: Python :: 3.6
Classifier: Programming Language :: Python :: 3.7
Classifier: Programming Language :: Python :: 3.8
Classifier: Programming Language :: Python :: 3.9
Classifier: Programming Language :: Python :: 3.10
Requires-Python: >=3.6, <4
License-File: LICENSE
